<DOMSymbolItem xmlns:xsi="http://www.w3.org/2001/XMLSchema-instance" xmlns="http://ns.adobe.com/xfl/2008/" name="元件/mc_038" itemID="64788eba-00000bae" lastModified="1685622459">
  <timeline>
    <DOMTimeline name="mc_038">
      <layers>
        <DOMLayer name="图层 1" color="#4FFF4F" current="true" isSelected="true">
          <frames>
            <DOMFrame index="0" keyMode="9728">
              <elements>
                <DOMBitmapInstance libraryItemName="图片/picture_036"/>
              </elements>
            </DOMFrame>
            <DOMFrame index="1" keyMode="9728">
              <elements>
                <DOMBitmapInstance selected="true" libraryItemName="图片/picture_315"/>
              </elements>
            </DOMFrame>
            <DOMFrame index="2" keyMode="9728">
              <elements>
                <DOMBitmapInstance libraryItemName="图片/picture_316"/>
              </elements>
            </DOMFrame>
          </frames>
        </DOMLayer>
      </layers>
    </DOMTimeline>
  </timeline>
</DOMSymbolItem>