<DOMSymbolItem xmlns:xsi="http://www.w3.org/2001/XMLSchema-instance" xmlns="http://ns.adobe.com/xfl/2008/" name="元件/mc_011" itemID="64a379d7-00000d5e" lastModified="1688435159">
  <timeline>
    <DOMTimeline name="mc_011">
      <layers>
        <DOMLayer name="图层 3" color="#FFFF4F" current="true" isSelected="true">
          <frames>
            <DOMFrame index="0" duration="2" keyMode="9728">
              <elements>
                <DOMBitmapInstance libraryItemName="图片/picture_076">
                  <matrix>
                    <Matrix tx="-4.25" ty="58.55"/>
                  </matrix>
                </DOMBitmapInstance>
              </elements>
            </DOMFrame>
            <DOMFrame index="2" duration="2" keyMode="9728">
              <elements>
                <DOMBitmapInstance libraryItemName="图片/picture_075">
                  <matrix>
                    <Matrix tx="-5.25" ty="63.55"/>
                  </matrix>
                </DOMBitmapInstance>
              </elements>
            </DOMFrame>
            <DOMFrame index="4" duration="2" keyMode="9728">
              <elements>
                <DOMBitmapInstance libraryItemName="图片/picture_074">
                  <matrix>
                    <Matrix tx="-5.25" ty="15.55"/>
                  </matrix>
                </DOMBitmapInstance>
                <DOMGroup>
                  <members>
                    <DOMShape>
                      <fills>
                        <FillStyle index="1">
                          <BitmapFill bitmapPath="图片/picture_074">
                            <matrix>
                              <Matrix a="20" d="20" tx="21.1" ty="-13.4"/>
                            </matrix>
                          </BitmapFill>
                        </FillStyle>
                      </fills>
                      <edges>
                        <Edge fillStyle1="1" edges="!2262 -268|2262 548!2262 548|1157 548!1157 548|1157 -268!1157 -268|2262 -268"/>
                      </edges>
                    </DOMShape>
                  </members>
                </DOMGroup>
              </elements>
            </DOMFrame>
            <DOMFrame index="6" duration="6" keyMode="9728">
              <elements>
                <DOMBitmapInstance libraryItemName="图片/picture_073">
                  <matrix>
                    <Matrix tx="-5.25" ty="12.55"/>
                  </matrix>
                </DOMBitmapInstance>
                <DOMGroup>
                  <members>
                    <DOMShape>
                      <fills>
                        <FillStyle index="1">
                          <BitmapFill bitmapPath="图片/picture_073">
                            <matrix>
                              <Matrix a="20" d="20" tx="8.6" ty="-4.9"/>
                            </matrix>
                          </BitmapFill>
                        </FillStyle>
                      </fills>
                      <edges>
                        <Edge fillStyle1="1" edges="!2012 -98|2012 496!2012 496|967 496!967 496|967 -98!967 -98|2012 -98"/>
                      </edges>
                    </DOMShape>
                  </members>
                </DOMGroup>
                <DOMGroup>
                  <members>
                    <DOMShape>
                      <fills>
                        <FillStyle index="1">
                          <BitmapFill bitmapPath="图片/picture_073">
                            <matrix>
                              <Matrix a="20" d="20" tx="20.6" ty="-19.9"/>
                            </matrix>
                          </BitmapFill>
                        </FillStyle>
                      </fills>
                      <edges>
                        <Edge fillStyle1="1" edges="!2252 -398|2252 196!2252 196|1207 196!1207 196|1207 -398!1207 -398|2252 -398"/>
                      </edges>
                    </DOMShape>
                  </members>
                </DOMGroup>
                <DOMGroup>
                  <members>
                    <DOMShape>
                      <fills>
                        <FillStyle index="1">
                          <BitmapFill bitmapPath="图片/picture_073">
                            <matrix>
                              <Matrix a="20" d="20" tx="33.1" ty="-34.9"/>
                            </matrix>
                          </BitmapFill>
                        </FillStyle>
                      </fills>
                      <edges>
                        <Edge fillStyle1="1" edges="!1457 -698|2502 -698!2502 -698|2502 -104!2502 -104|1457 -104!1457 -104|1457 -698"/>
                      </edges>
                    </DOMShape>
                  </members>
                </DOMGroup>
                <DOMGroup>
                  <members>
                    <DOMShape>
                      <fills>
                        <FillStyle index="1">
                          <BitmapFill bitmapPath="图片/picture_073">
                            <matrix>
                              <Matrix a="20" d="20" tx="45.1" ty="-49.9"/>
                            </matrix>
                          </BitmapFill>
                        </FillStyle>
                      </fills>
                      <edges>
                        <Edge fillStyle1="1" edges="!2742 -404|1697 -404!1697 -404|1697 -998!1697 -998|2742 -998!2742 -998|2742 -404"/>
                      </edges>
                    </DOMShape>
                  </members>
                </DOMGroup>
              </elements>
            </DOMFrame>
            <DOMFrame index="12" duration="2" keyMode="9728">
              <elements>
                <DOMBitmapInstance libraryItemName="图片/picture_074">
                  <matrix>
                    <Matrix tx="-5.25" ty="15.55"/>
                  </matrix>
                </DOMBitmapInstance>
              </elements>
            </DOMFrame>
            <DOMFrame index="14" duration="2" keyMode="9728">
              <elements>
                <DOMBitmapInstance libraryItemName="图片/picture_075">
                  <matrix>
                    <Matrix tx="-5.25" ty="63.55"/>
                  </matrix>
                </DOMBitmapInstance>
              </elements>
            </DOMFrame>
            <DOMFrame index="16" duration="10" keyMode="9728">
              <elements>
                <DOMBitmapInstance libraryItemName="图片/picture_076">
                  <matrix>
                    <Matrix tx="-4.25" ty="58.55"/>
                  </matrix>
                </DOMBitmapInstance>
              </elements>
            </DOMFrame>
          </frames>
        </DOMLayer>
      </layers>
    </DOMTimeline>
  </timeline>
</DOMSymbolItem>