<DOMSymbolItem xmlns:xsi="http://www.w3.org/2001/XMLSchema-instance" xmlns="http://ns.adobe.com/xfl/2008/" name="元件/mc_007" itemID="65fc5ce7-000009c7" sourceFlashFilepath="../itachi.fla" sourceLibraryItemHRef="AI面" sourceLastModified="1319512457" lastModified="1711037671" lastUniqueIdentifier="44" sourceItemID="00000000-ffffffff">
  <timeline>
    <DOMTimeline name="mc_007" currentFrame="1">
      <layers>
        <DOMLayer name="tkmain" color="#4FFF4F" locked="true" autoNamed="false">
          <frames>
            <DOMFrame index="0" keyMode="9728">
              <Actionscript>
                <script><![CDATA[stop();]]></script>
              </Actionscript>
              <elements/>
            </DOMFrame>
            <DOMFrame index="1" keyMode="9728">
              <elements>
                <DOMSymbolInstance libraryItemName="元件/mc_036" name="tkanmian">
                  <matrix>
                    <Matrix a="1.5478515625" d="2.61672973632813" tx="1.3" ty="-82.9"/>
                  </matrix>
                  <transformationPoint>
                    <Point x="66.6" y="41.6"/>
                  </transformationPoint>
                </DOMSymbolInstance>
              </elements>
            </DOMFrame>
          </frames>
        </DOMLayer>
        <DOMLayer name="tzmian" color="#9933CC" locked="true" autoNamed="false">
          <frames>
            <DOMFrame index="0" keyMode="9728">
              <elements/>
            </DOMFrame>
            <DOMFrame index="1" keyMode="9728">
              <elements>
                <DOMSymbolInstance libraryItemName="元件/mc_036" name="tzmian">
                  <matrix>
                    <Matrix a="5.4560546875" d="5.92033386230469" tx="-167.9" ty="-124.2"/>
                  </matrix>
                  <transformationPoint>
                    <Point x="0.3" y="1.2"/>
                  </transformationPoint>
                </DOMSymbolInstance>
              </elements>
            </DOMFrame>
          </frames>
        </DOMLayer>
        <DOMLayer name="kanmian" color="#FFFF4F" locked="true" autoNamed="false">
          <frames>
            <DOMFrame index="0" keyMode="9728">
              <elements/>
            </DOMFrame>
            <DOMFrame index="1" keyMode="9728">
              <elements>
                <DOMSymbolInstance libraryItemName="元件/mc_036" name="kanmian">
                  <matrix>
                    <Matrix a="1.48654174804688" d="1.40071105957031" tx="10.3" ty="-50.25"/>
                  </matrix>
                  <transformationPoint>
                    <Point x="0.3" y="1.2"/>
                  </transformationPoint>
                </DOMSymbolInstance>
              </elements>
            </DOMFrame>
          </frames>
        </DOMLayer>
        <DOMLayer name="kj1mian" color="#FF4FFF" locked="true" autoNamed="false">
          <frames>
            <DOMFrame index="0" keyMode="9728">
              <elements/>
            </DOMFrame>
            <DOMFrame index="1" keyMode="9728">
              <elements>
                <DOMSymbolInstance libraryItemName="元件/mc_036" name="kj1mian">
                  <matrix>
                    <Matrix a="2.47453308105469" d="2.56156921386719" tx="6.2" ty="-80.7"/>
                  </matrix>
                  <transformationPoint>
                    <Point x="0.35" y="1.25"/>
                  </transformationPoint>
                </DOMSymbolInstance>
              </elements>
            </DOMFrame>
          </frames>
        </DOMLayer>
        <DOMLayer name="kj2mian" color="#4FFFFF" locked="true" autoNamed="false">
          <frames>
            <DOMFrame index="0" keyMode="9728">
              <elements/>
            </DOMFrame>
            <DOMFrame index="1" keyMode="9728">
              <elements>
                <DOMSymbolInstance libraryItemName="元件/mc_036" name="kj2mian">
                  <matrix>
                    <Matrix a="2.36569213867188" d="4.52703857421875" tx="-11.7" ty="-159.5"/>
                  </matrix>
                  <transformationPoint>
                    <Point x="0.3" y="1.35"/>
                  </transformationPoint>
                </DOMSymbolInstance>
              </elements>
            </DOMFrame>
          </frames>
        </DOMLayer>
        <DOMLayer name="zh1mian" color="#808080" locked="true" autoNamed="false">
          <frames>
            <DOMFrame index="0" keyMode="9728">
              <elements/>
            </DOMFrame>
            <DOMFrame index="1" keyMode="9728">
              <elements>
                <DOMSymbolInstance libraryItemName="元件/mc_036" name="zh1mian">
                  <matrix>
                    <Matrix a="5.96479797363281" d="4.94081115722656" tx="5.35" ty="-210.55"/>
                  </matrix>
                  <transformationPoint>
                    <Point x="0.25" y="1.25"/>
                  </transformationPoint>
                </DOMSymbolInstance>
              </elements>
            </DOMFrame>
          </frames>
        </DOMLayer>
        <DOMLayer name="zh2mian" color="#4F80FF" locked="true" autoNamed="false">
          <frames>
            <DOMFrame index="0" keyMode="9728">
              <elements/>
            </DOMFrame>
            <DOMFrame index="1" keyMode="9728">
              <elements>
                <DOMSymbolInstance libraryItemName="元件/mc_036" name="zh2mian">
                  <matrix>
                    <Matrix a="22.7447967529297" d="2.63558959960938" tx="-750" ty="-83.05"/>
                  </matrix>
                  <transformationPoint>
                    <Point x="0.15" y="1.3"/>
                  </transformationPoint>
                </DOMSymbolInstance>
              </elements>
            </DOMFrame>
          </frames>
        </DOMLayer>
        <DOMLayer name="zh3mian" color="#FF4F4F" locked="true" autoNamed="false">
          <frames>
            <DOMFrame index="0" keyMode="9728">
              <elements/>
            </DOMFrame>
            <DOMFrame index="1" keyMode="9728">
              <elements>
                <DOMSymbolInstance libraryItemName="元件/mc_036" name="zh3mian">
                  <matrix>
                    <Matrix a="22.7449645996094" b="0.0001220703125" c="-0.0001983642578125" d="14.8146209716797" tx="-750" ty="-300"/>
                  </matrix>
                  <transformationPoint>
                    <Point x="0.2" y="1.4"/>
                  </transformationPoint>
                </DOMSymbolInstance>
              </elements>
            </DOMFrame>
          </frames>
        </DOMLayer>
        <DOMLayer name="bsmian" color="#4FFF4F" locked="true" autoNamed="false">
          <frames>
            <DOMFrame index="0" keyMode="9728">
              <elements/>
            </DOMFrame>
            <DOMFrame index="1" keyMode="9728">
              <elements>
                <DOMSymbolInstance libraryItemName="元件/mc_036" name="bsmian">
                  <matrix>
                    <Matrix a="6.43820190429688" b="-0.0010833740234375" c="0.0008544921875" d="5.34201049804688" tx="1.5" ty="-194.45"/>
                  </matrix>
                  <transformationPoint>
                    <Point x="0.15" y="1.4"/>
                  </transformationPoint>
                </DOMSymbolInstance>
              </elements>
            </DOMFrame>
          </frames>
        </DOMLayer>
        <DOMLayer name="sbsmian" color="#9933CC" locked="true" autoNamed="false">
          <frames>
            <DOMFrame index="0" keyMode="9728">
              <elements/>
            </DOMFrame>
            <DOMFrame index="1" keyMode="9728">
              <elements>
                <DOMSymbolInstance libraryItemName="元件/mc_036" name="sbsmian">
                  <matrix>
                    <Matrix a="22.7449645996094" b="0.0001220703125" c="-0.0001983642578125" d="14.8146209716797" tx="-750" ty="-300"/>
                  </matrix>
                  <transformationPoint>
                    <Point x="0.2" y="1.4"/>
                  </transformationPoint>
                </DOMSymbolInstance>
              </elements>
            </DOMFrame>
          </frames>
        </DOMLayer>
        <DOMLayer name="kbsmian" color="#9933CC" locked="true" autoNamed="false">
          <frames>
            <DOMFrame index="0" keyMode="9728">
              <elements/>
            </DOMFrame>
            <DOMFrame index="1" keyMode="9728">
              <elements>
                <DOMSymbolInstance libraryItemName="元件/mc_036" name="kbsmian">
                  <matrix>
                    <Matrix a="2.51553344726563" b="-0.000396728515625" c="0.000732421875" d="4.53324890136719" tx="-38.15" ty="-62.2"/>
                  </matrix>
                  <transformationPoint>
                    <Point x="0.15" y="1.65"/>
                  </transformationPoint>
                </DOMSymbolInstance>
              </elements>
            </DOMFrame>
          </frames>
        </DOMLayer>
        <DOMLayer name="cbsmian" color="#FFFF4F" current="true" isSelected="true" autoNamed="false">
          <frames>
            <DOMFrame index="0" keyMode="9728">
              <elements/>
            </DOMFrame>
            <DOMFrame index="1" keyMode="9728">
              <elements>
                <DOMSymbolInstance libraryItemName="元件/mc_036" name="cbsmian">
                  <matrix>
                    <Matrix a="1.88160705566406" b="-0.0002899169921875" c="0.0005035400390625" d="3.16973876953125" tx="-12.9" ty="-99.65"/>
                  </matrix>
                  <transformationPoint>
                    <Point x="0.25" y="1.5"/>
                  </transformationPoint>
                </DOMSymbolInstance>
              </elements>
            </DOMFrame>
          </frames>
        </DOMLayer>
      </layers>
    </DOMTimeline>
  </timeline>
</DOMSymbolItem>