<DOMSymbolItem xmlns:xsi="http://www.w3.org/2001/XMLSchema-instance" xmlns="http://ns.adobe.com/xfl/2008/" name="元件/mc_013" itemID="624bb859-00007f70" lastModified="1649129561">
  <timeline>
    <DOMTimeline name="mc_013" currentFrame="19">
      <layers>
        <DOMLayer name="图层 3" color="#FF800A" current="true" isSelected="true">
          <frames>
            <DOMFrame index="0" duration="2" keyMode="9728">
              <elements>
                <DOMBitmapInstance libraryItemName="图片/picture_079">
                  <matrix>
                    <Matrix tx="12.45" ty="66.5"/>
                  </matrix>
                </DOMBitmapInstance>
              </elements>
            </DOMFrame>
            <DOMFrame index="2" duration="2" keyMode="9728">
              <elements>
                <DOMBitmapInstance libraryItemName="图片/picture_080">
                  <matrix>
                    <Matrix tx="7.45" ty="66.5"/>
                  </matrix>
                </DOMBitmapInstance>
              </elements>
            </DOMFrame>
            <DOMFrame index="4" duration="5" keyMode="9728">
              <elements>
                <DOMBitmapInstance selected="true" libraryItemName="图片/picture_081">
                  <matrix>
                    <Matrix tx="12.45" ty="66.5"/>
                  </matrix>
                </DOMBitmapInstance>
              </elements>
            </DOMFrame>
            <DOMFrame index="9" duration="2" keyMode="9728">
              <elements>
                <DOMBitmapInstance libraryItemName="图片/picture_038">
                  <matrix>
                    <Matrix tx="11" ty="55.6"/>
                  </matrix>
                </DOMBitmapInstance>
              </elements>
            </DOMFrame>
            <DOMFrame index="11" duration="4" keyMode="9728">
              <elements/>
            </DOMFrame>
            <DOMFrame index="15" duration="2" keyMode="9728">
              <elements>
                <DOMBitmapInstance selected="true" libraryItemName="图片/picture_038">
                  <matrix>
                    <Matrix tx="11" ty="55.6"/>
                  </matrix>
                </DOMBitmapInstance>
              </elements>
            </DOMFrame>
            <DOMFrame index="17" duration="2" keyMode="9728">
              <elements>
                <DOMBitmapInstance libraryItemName="图片/picture_081">
                  <matrix>
                    <Matrix tx="12.45" ty="66.5"/>
                  </matrix>
                </DOMBitmapInstance>
              </elements>
            </DOMFrame>
            <DOMFrame index="19" duration="2" keyMode="9728">
              <elements>
                <DOMBitmapInstance libraryItemName="图片/picture_083">
                  <matrix>
                    <Matrix tx="12.45" ty="70.5"/>
                  </matrix>
                </DOMBitmapInstance>
              </elements>
            </DOMFrame>
            <DOMFrame index="21" duration="2" keyMode="9728">
              <elements>
                <DOMBitmapInstance libraryItemName="图片/picture_082">
                  <matrix>
                    <Matrix tx="12.45" ty="70.5"/>
                  </matrix>
                </DOMBitmapInstance>
              </elements>
            </DOMFrame>
            <DOMFrame index="23" duration="3" keyMode="9728">
              <elements>
                <DOMBitmapInstance libraryItemName="图片/picture_083">
                  <matrix>
                    <Matrix tx="12.45" ty="70.5"/>
                  </matrix>
                </DOMBitmapInstance>
              </elements>
            </DOMFrame>
            <DOMFrame index="26" duration="2" keyMode="9728">
              <elements>
                <DOMBitmapInstance libraryItemName="图片/picture_084">
                  <matrix>
                    <Matrix tx="12.45" ty="70.5"/>
                  </matrix>
                </DOMBitmapInstance>
              </elements>
            </DOMFrame>
            <DOMFrame index="28" duration="25" keyMode="9728">
              <elements>
                <DOMBitmapInstance libraryItemName="图片/picture_085">
                  <matrix>
                    <Matrix tx="12.45" ty="70.5"/>
                  </matrix>
                </DOMBitmapInstance>
              </elements>
            </DOMFrame>
          </frames>
        </DOMLayer>
      </layers>
    </DOMTimeline>
  </timeline>
</DOMSymbolItem>