<DOMSymbolItem xmlns:xsi="http://www.w3.org/2001/XMLSchema-instance" xmlns="http://ns.adobe.com/xfl/2008/" name="元件/mc_031" itemID="624bdab3-00001d61" sourceFlashFilepath="../../cs3/rukia.fla" sourceLibraryItemHRef="露琪亚/露琪亚-站 副本 3" sourceLastModified="1323932723" lastModified="1649138355" sourceItemID="00000000-ffffffff">
  <timeline>
    <DOMTimeline name="mc_031">
      <layers>
        <DOMLayer name="图层 7" color="#9933CC" current="true" isSelected="true">
          <frames>
            <DOMFrame index="0" keyMode="9728">
              <elements>
                <DOMBitmapInstance libraryItemName="图片/picture_440">
                  <matrix>
                    <Matrix tx="-2.75" ty="-3.75"/>
                  </matrix>
                </DOMBitmapInstance>
              </elements>
            </DOMFrame>
          </frames>
        </DOMLayer>
      </layers>
    </DOMTimeline>
  </timeline>
</DOMSymbolItem>